RAM_Engine_Verilog/Operand_Storage_System/r_a_mE.v
module ram_engine(
    input [3:0] data_in,
    input sel,
    input store_clk, 
    output reg [3:0] d_ff1,
    output reg [3:0] d_ff2
);

  initial d_ff1 = 4'h0;
  initial d_ff2 = 4'h0;
  
  always@ (posedge store_clk) begin
    if (sel == 1  & store_clk == 1) begin
        d_ff2 = data_in;
    end else if (sel == 0 & store_clk == 1) begin
        d_ff1 = data_in;
    end
  end
endmodule

RAM_Engine_Verilog/Operand_Storage_System/r_a_mE_tb.v
`include "r_a_mE.v"

module testbench;

  reg [3:0] data_in_t;
  reg sel_t;
  reg store_clkt;
  wire [3:0] d_ff1t;
  wire [3:0] d_ff2t;
  
  ram_engine dut(
    .data_in(data_in_t),
    .sel(sel_t),
    .store_clk(store_clkt),
    .d_ff1(d_ff1t),
    .d_ff2(d_ff2t)
  );

  initial begin

    $monitor("t=%0t | data_in = %b | sel_t = %b | store_t = %b | d_ff1t = %b | dff2t = %b", $time, data_in_t, sel_t, store_clkt, d_ff1t, d_ff2t);
    $dumpfile("Sim.vcd");
    $dumpvars(0, testbench);

    data_in_t = 4'b1011;
    store_clkt = 0;
    sel_t = 1;
    #5;

    data_in_t = 4'b1011;
    store_clkt = 1;
    sel_t = 1;
    #5;

    data_in_t = 4'b1000;
    store_clkt = 1;
    sel_t = 0;
    #5;

    data_in_t = 4'b1000;
    store_clkt = 0;
    sel_t = 0;
    #5;

    data_in_t = 4'b1000;
    store_clkt = 1;
    sel_t = 1;
    #5;

    data_in_t = 4'b1010;
    store_clkt = 0;
    sel_t = 0;
    #5;

    data_in_t = 4'b1010;
    store_clkt = 1;
    sel_t = 1;
    #5;

    data_in_t = 4'b0000;
    store_clkt = 0;
    sel_t = 1;
    #5;

    data_in_t = 4'b1100;
    store_clkt = 0;
    sel_t = 0;
    #5;

    data_in_t = 4'b1100;
    store_clkt = 1;
    sel_t = 0;
    #5;


    $display("Simulation Complete!");
    $finish;
  end
endmodule

RAM_Engine_Verilog/Operand_Storage_System/Sim.vcd
$date
	Mon Jan 19 21:21:36 2026
$end
$version
	Icarus Verilog
$end
$timescale
	1s
$end
$scope module testbench $end
$var wire 4 ! d_ff2t [3:0] $end
$var wire 4 " d_ff1t [3:0] $end
$var reg 4 # data_in_t [3:0] $end
$var reg 1 $ sel_t $end
$var reg 1 % store_clkt $end
$scope module dut $end
$var wire 4 & data_in [3:0] $end
$var wire 1 $ sel $end
$var wire 1 % store_clk $end
$var reg 4 ' d_ff1 [3:0] $end
$var reg 4 ( d_ff2 [3:0] $end
$upscope $end
$upscope $end
$enddefinitions $end
$comment Show the parameter values. $end
$dumpall
$end
#0
$dumpvars
b0 (
b0 '
b1011 &
0%
1$
b1011 #
b0 "
b0 !
$end
#5
b1011 !
b1011 (
1%
#10
0$
b1000 #
b1000 &
#15
0%
#20
b1000 !
b1000 (
1$
1%
#25
0$
0%
b1010 #
b1010 &
#30
b1010 !
b1010 (
1$
1%
#35
0%
b0 #
b0 &
#40
0$
b1100 #
b1100 &
#45
b1100 "
b1100 '
1%
