RAM_Engine/RAM_Engine_Verilog/Operand_Storage_System/r_a_mE.v
// ============================================================
// Module : operand_storage_system
// Purpose: Stores a 4-bit operand into one of two registers
//          based on a select signal. Acts as a 2-slot register
//          bank where each slot holds one operand for Computation.
//
// Inputs:
//   data_in   [3:0] - The 4-bit operand to be stored
//   sel             - Selects destination register (0 = d_ff1, 1 = d_ff2)
//   store_clk       - Rising edge triggers the store operation
//   reset           - Asynchronous active-high reset, clears both registers
//
// Outputs:
//   d_ff1     [3:0] - Register slot 1, holds operand when sel = 0
//   d_ff2     [3:0] - Register slot 2, holds operand when sel = 1
//
// Behavior:
//   - On posedge store_clk : routes data_in to d_ff1 or d_ff2 via sel
//   - On posedge reset     : immediately clears both registers (async)
//   - Data is retained until overwritten or reset is asserted
// ============================================================
module operand_storage_system(
    input  [3:0] data_in,   // 4-bit input data (operand to be stored)
    input        sel,       // Select line: 0 → store in d_ff1, 1 → store in d_ff2
    input        store_clk, // Manual clock trigger (storage happens on rising edge)
    input        reset,     // Asynchronous reset (immediate clear of registers)
    output reg [3:0] d_ff1, // First 4-bit register (operand slot 1)
    output reg [3:0] d_ff2  // Second 4-bit register (operand slot 2)
);

// ============================================================
// Sequential Logic Block
// ============================================================
// Sensitivity list includes both store_clk and reset so that:
//   - Normal storage is clocked (synchronous with store_clk)
//   - Reset is asynchronous (does not wait for clock edge)
always @(posedge store_clk or posedge reset) begin
    
    // ----------------------------------------------------------
    // Asynchronous Reset
    // ----------------------------------------------------------
    // Triggered immediately when reset goes HIGH, independent of
    // the clock. Both registers are cleared to 0000 instantly.
    // This ensures a known clean state on power-up or system reset.
    if (reset) begin
        d_ff1 <= 4'b0000; // Clear register 1 → slot 1 holds 0
        d_ff2 <= 4'b0000; // Clear register 2 → slot 2 holds 0
    
    end else begin
        // ------------------------------------------------------
        // Normal Clocked Operation
        // ------------------------------------------------------
        // On each rising edge of store_clk, data_in is routed
        // to the appropriate register depending on sel.
        // Only one register is written per clock cycle.
        // The other register retains its previous value.
        
        if (sel)
            d_ff2 <= data_in; // sel = 1 → write data_in into register 2
        else
            d_ff1 <= data_in; // sel = 0 → write data_in into register 1
    end
end

endmodule

RAM_Engine/RAM_Engine_Verilog/Operand_Storage_System/r_a_mE_tb.v
`include "r_a_mE.v"

// Testbench for operand_storage_system
// This module stimulates the DUT (Design Under Test)
// and observes how data is stored in registers.

module testbench;

  // Testbench signals (inputs to DUT)
  reg [3:0] data_in_t;   // Input data stimulus
  reg sel_t;             // Select line stimulus
  reg reset_t;           // Reset signal stimulus
  reg store_clkt;        // Manual clock stimulus

  // Outputs from DUT (observed signals)
  wire [3:0] d_ff1t;     
  wire [3:0] d_ff2t;
  
  // Instantiate DUT (Device Under Test)
  operand_storage_system dut(
    .data_in(data_in_t),
    .sel(sel_t),
    .store_clk(store_clkt),
    .reset(reset_t),
    .d_ff1(d_ff1t),
    .d_ff2(d_ff2t)
  );

  initial begin

    // Monitor prints values whenever any listed signal changes
    // Helps track behavior over simulation time
    $monitor("t=%0t | data_in = %b | sel_t = %b | store_t = %b | reset_t = %b | d_ff1t = %b | dff2t = %b",
              $time, data_in_t, sel_t, store_clkt, reset_t, d_ff1t, d_ff2t);

    // VCD dump for waveform viewing (GTKWave)
    $dumpfile("Sim.vcd");
    $dumpvars(0, testbench);
   
    // -------- Test Sequence Begins --------

    // Initial state: no clock edge yet → no storage should happen
    data_in_t = 4'b1000;
    store_clkt = 0;
    sel_t = 0;
    reset_t = 0;
    #5;

    // Rising edge → store 1000 into d_ff1 (sel = 0)
    data_in_t = 4'b1000;
    store_clkt = 1;
    sel_t = 0;
    reset_t = 0;
    #5;

    // Reset asserted → both registers should clear immediately
    data_in_t = 4'b0000;
    store_clkt = 1;
    sel_t = 1;
    reset_t = 1;
    #5;

    // Prepare next input (no clock edge yet → no write)
    data_in_t = 4'b1011;
    store_clkt = 0;
    sel_t = 1;
    reset_t = 0;
    #5;

    // Rising edge → store 1011 into d_ff2 (sel = 1)
    data_in_t = 4'b1011;
    store_clkt = 1;
    sel_t = 1;
    reset_t = 0;
    #5;

    // Prepare next input for d_ff1 (no write yet)
    data_in_t = 4'b1111;
    store_clkt = 0;
    sel_t = 0;
    reset_t = 0;
    #5;

    // Rising edge → store 1111 into d_ff1
    data_in_t = 4'b1111;
    store_clkt = 1;
    sel_t = 0;
    reset_t = 0;
    #5;

    // Direct write to d_ff2 (clock already high → no edge, so no write)
    data_in_t = 4'b1001;
    store_clkt = 1;
    sel_t = 1;
    reset_t = 0;
    #5;

    // Prepare next input (no clock edge)
    data_in_t = 4'b0001;
    store_clkt = 0;
    sel_t = 0;
    reset_t = 0;
    #5;

    // Reset again → both registers cleared
    data_in_t = 4'b1101;
    store_clkt = 0;
    sel_t = 1;
    reset_t = 1;
    #5;

    // Even with clock edge, reset dominates → still cleared
    data_in_t = 4'b1101;
    store_clkt = 1;
    sel_t = 1;
    reset_t = 1;
    #5;

    // -------- End of Simulation --------
    $display("Simulation Complete!");
    $finish;
  end

endmodule

RAM_Engine_Verilog/Operand_Storage_System/Sim.vcd
$date
	Tue Jan 20 12:51:04 2026
$end
$version
	Icarus Verilog
$end
$timescale
	1s
$end
$scope module testbench $end
$var wire 4 ! d_ff2t [3:0] $end
$var wire 4 " d_ff1t [3:0] $end
$var reg 4 # data_in_t [3:0] $end
$var reg 1 $ reset_t $end
$var reg 1 % sel_t $end
$var reg 1 & store_clkt $end
$scope module dut $end
$var wire 4 ' data_in [3:0] $end
$var wire 1 $ reset $end
$var wire 1 % sel $end
$var wire 1 & store_clk $end
$var reg 4 ( d_ff1 [3:0] $end
$var reg 4 ) d_ff2 [3:0] $end
$upscope $end
$upscope $end
$enddefinitions $end
$comment Show the parameter values. $end
$dumpall
$end
#0
$dumpvars
bx )
bx (
b1000 '
0&
0%
0$
b1000 #
bx "
bx !
$end
#5
b1000 "
b1000 (
1&
#10
b0 !
b0 )
b0 "
b0 (
1$
1%
b0 #
b0 '
#15
0$
0&
b1011 #
b1011 '
#20
b1011 !
b1011 )
1&
#25
0%
0&
b1111 #
b1111 '
#30
b1111 "
b1111 (
1&
#35
1%
b1001 #
b1001 '
#40
0%
0&
b1 #
b1 '
#45
b0 !
b0 )
b0 "
b0 (
1$
1%
b1101 #
b1101 '
